calmcode/__init__.py
calmcode/challenge/__init__.py
calmcode/challenge/_challenge.py
calmcode/challenge/sailship.py
calmcode/challenge/tsp.py
tests/__init__.py
tests/test_travelling_sales_ship.py
calmcode-0.0.4.dist-info/METADATA
calmcode-0.0.4.dist-info/WHEEL
calmcode-0.0.4.dist-info/top_level.txt
calmcode-0.0.4.dist-info/RECORD
